examples/__init__.py
examples/basic.py
gui/__init__.py
gui/sf10/__init__.py
gui/sf10/design.py
gui/sf10/main.py
vapourtec/__init__.py
vapourtec/__version__.py
vapourtec/errors.py
vapourtec/sf10.py
vapourtec-1.2.1.dist-info/LICENSE
vapourtec-1.2.1.dist-info/METADATA
vapourtec-1.2.1.dist-info/WHEEL
vapourtec-1.2.1.dist-info/top_level.txt
vapourtec-1.2.1.dist-info/RECORD
