Metadata-Version: 2.1
Name: vapourtec
Version: 1.2.1
Summary: An unofficial package to control Vapourtec products; we are not affliated with Vapourtec.
Home-page: https://gitlab.com/heingroup/vapourtec
Author: Veronica Lai // Hein Group
License: UNKNOWN
Platform: UNKNOWN
Classifier: Programming Language :: Python :: 3
Requires-Python: >=3.6
License-File: LICENSE
Requires-Dist: ftdi-serial
